setup.py
envoy/__init__.py
envoy/core.py
envoy.egg-info/PKG-INFO
envoy.egg-info/SOURCES.txt
envoy.egg-info/dependency_links.txt
envoy.egg-info/top_level.txt