Metadata-Version: 1.0
Name: envoy
Version: 0.0.1
Summary: Simple API for running external processes.
Home-page: https://github.com/kennethreitz/envoy
Author: Kenneth Reitz
Author-email: me@kennethreitz.com
License: MIT
Platform: UNKNOWN
Classifier: Development Status :: 5 - Production/Stable
Classifier: Intended Audience :: Developers
Classifier: Natural Language :: English
Classifier: License :: OSI Approved :: MIT License
Classifier: Programming Language :: Python
Classifier: Programming Language :: Python :: 2.5
Classifier: Programming Language :: Python :: 2.6
Classifier: Programming Language :: Python :: 2.7
